Workbook
Name Slicer_product: #N/A
Name Slicer_region: #N/A

Sheet Task Checklist
A1: WEEK 3 — DAY 3: EXCEL FOR ANALYSIS
A2: Submission readiness checklist — based on the Cynaris lesson PDF
A4: Requirement | B4: Current status | C4: What remains / honest note
A5: Revenue by region, product, and quarter | B5: PARTIAL — formula summaries included | C5: The Analysis sheet has formula-based summaries. These are not a native Excel PivotTable.
A6: Calculated fields: margin and growth % | B6: PARTIAL | C6: Growth formulas are included. Profit/margin cannot be calculated without cost data; do not invent costs.
A7: Power Query: combine multiple CSVs | B7: SCRIPT INCLUDED — connection not embedded | C7: PowerQuery_Combine_CSVs.m and three source CSVs are included. A real query connection must be created in compatible Excel.
A8: PivotChart with dynamic slicers | B8: NOT COMPLETE | C8: Existing charts are standard charts, not a native PivotChart with interactive slicers.
A9: Conditional formatting for KPI thresholds | B9: PARTIAL / PRESENT FOR GROWTH | C9: Growth cells have conditional formatting in the workbook; inspect the Analysis sheet.
A10: Git commit, push, and Pull Request | B10: NOT VERIFIED | C10: Must be done in the repository; this ZIP alone does not prove Git submission.
A11: Work log and CIA activities | B11: NOT VERIFIED | C11: Record the deliverable and CIA session/insights as required by the lesson.

Sheet Sheet1
A3: Row Labels | B3: Sum of amount
A4: Q1 | B4: 130000
A5: North | B5: 130000
A6: Laptop | B6: 85000
A7: Phone | B7: 45000
A8: Q2 | B8: 32000
A9: North | B9: 32000
A10: Tablet | B10: 32000
A11: Grand Total | B11: 162000

Sheet Sales Data
A1: id | B1: product | C1: region | D1: amount | E1: sale_date | F1: quantity | G1: discount | H1: cost | I1: profit | J1: margin_pct | K1: quarter
A2: 1 | B2: Laptop | C2: North | D2: 85000 | E2: 2026-01-15 | F2: 2 | G2: 0.05 | I2: =IF(H2="","",D2-H2) | J2: =IF(OR(H2="",D2=0),"",(D2-H2)/D2) | K2: ="Q"&ROUNDUP(MONTH(E2)/3,0) -> Q1
A3: 5 | B3: Phone | C3: North | D3: 45000 | E3: 2026-02-05 | F3: 4 | G3: 0.05 | I3: =IF(H3="","",D3-H3) | J3: =IF(OR(H3="",D3=0),"",(D3-H3)/D3) | K3: ="Q"&ROUNDUP(MONTH(E3)/3,0) -> Q1
A4: 7 | B4: Tablet | C4: North | D4: 32000 | E4: 2026-04-01 | F4: 2 | G4: 0.08 | I4: =IF(H4="","",D4-H4) | J4: =IF(OR(H4="",D4=0),"",(D4-H4)/D4) | K4: ="Q"&ROUNDUP(MONTH(E4)/3,0) -> Q2

Sheet Analysis
A1: NORTH SALES — ANALYSIS WORKBOOK
A2: Source: north_sales.csv (3 original records). Revenue is represented by amount.
A4: Revenue by Region | D4: Revenue by Quarter
A5: Region | B5: Revenue | D5: Quarter | E5: Revenue
A6: North | B6: =SUMIF('Sales Data'!$C:$C,A6,'Sales Data'!$D:$D) -> 162000 | D6: Q1 | E6: =SUMIF('Sales Data'!$K:$K,D6,'Sales Data'!$D:$D) -> 130000
D7: Q2 | E7: =SUMIF('Sales Data'!$K:$K,D7,'Sales Data'!$D:$D) -> 32000
D8: Q3 | E8: =SUMIF('Sales Data'!$K:$K,D8,'Sales Data'!$D:$D) -> 0
A9: Revenue by Product | D9: Q4 | E9: =SUMIF('Sales Data'!$K:$K,D9,'Sales Data'!$D:$D) -> 0
A10: Product | B10: Revenue
A11: Laptop | B11: =SUMIF('Sales Data'!$B:$B,A11,'Sales Data'!$D:$D) -> 85000
A12: Phone | B12: =SUMIF('Sales Data'!$B:$B,A12,'Sales Data'!$D:$D) -> 45000
A13: Tablet | B13: =SUMIF('Sales Data'!$B:$B,A13,'Sales Data'!$D:$D) -> 32000
A16: Quarter-over-Quarter Growth | D16: Profit Margin KPI
A17: Quarter | B17: Revenue | C17: Growth % | D17: Status | E17: Margin unavailable
A18: Q1 | B18: =E6 -> 130000 | C18: ="N/A (first quarter)" -> N/A (first quarter) | D18: Reason | E18: Source data has no cost values.
A19: Q2 | B19: =E7 -> 32000 | C19: =IF(B18=0,"N/A",(B19-B18)/B18) -> -0.75384615
A20: Q3 | B20: =E8 -> 0 | C20: =IF(B19=0,"N/A",(B20-B19)/B19) -> -1 | D20: Data limitation | E20: All 3 source records are North; Q3/Q4 have no sales. Profit/margin remain blank until verified costs are entered.
A21: Q4 | B21: =E9 -> 0 | C21: =IF(B20=0,"N/A",(B21-B20)/B20) -> N/A

Sheet Power Query
A1: POWER QUERY — COMBINE MULTIPLE CSV FILES
A3: Ready-to-use M code
A4: The full M script is also included as PowerQuery_Combine_CSVs.m in the deliverable ZIP. In Excel: Data > Get Data > From Other Sources > Blank Query > Advanced Editor; paste the code, then replace the folder path.
A6: Important | B6: Excel's native Power Query connection is not embedded by this generated workbook. The M script is provided ready to paste into Power Query; update its folder path and Close & Load.
A8: M code
A9: let
A10: // Put north_sales_part1.csv, north_sales_part2.csv, and north_sales_part3.csv in one folder.
A11: // Change this folder path to the folder where you saved the source_csvs files.
A12: Source = Folder.Files("C:\\CHANGE_ME\\source_csvs"),
A13: CsvFiles = Table.SelectRows(Source, each Text.Lower([Extension]) = ".csv"),
A14: ReadCsv = Table.AddColumn(CsvFiles, "Data", each
A15: Table.PromoteHeaders(
A16: Csv.Document([Content], [Delimiter=",", Encoding=65001, QuoteStyle=QuoteStyle.Csv]),
A17: [PromoteAllScalars=true]
A18: )
A19: ),
... A35: AddMargin

Sheet Read Me
A1: WEEK 3 — DAY 3: EXCEL FOR ANALYSIS
A2: Requirement from Cynaris lesson | B2: Current status / action
A3: Revenue by region, product and quarter | B3: Formula-based summaries are present on Analysis. A native Excel PivotTable is not embedded.
A4: Calculated margin and growth % | B4: Growth formulas are present. Profit/margin remain blank because the source data has no cost values; do not invent costs.
A5: Power Query: import, transform and load multiple CSVs | B5: PowerQuery_Combine_CSVs.m and three source CSV files are included. The native query connection is not embedded; create it in compatible Excel and Close & Load.
A6: PivotChart with dynamic slicers | B6: The existing charts are standard charts, not a native PivotChart with interactive slicers.
A7: Conditional formatting for KPI thresholds | B7: Growth cells have conditional formatting. Growth is not meaningful where the previous quarter has zero revenue.
A8: Source data integrity | B8: Only the three original sales records are used. They are split across three CSVs to demonstrate combining files; no extra sales have been fabricated.
A9: IMPORTANT: before calling this fully complete | B9: Complete the three Excel-only actions below: (1) create a native PivotTable, (2) connect and load Power Query, (3) create PivotChart + slicers. Save the workbook after each step.
A10: Native PivotTable steps | B10: Select any cell in Sales Data > Insert > PivotTable > New Worksheet. Add region, product and quarter to Rows (or arrange as needed); add amount to Values and ensure it is Sum. Rename sheet PivotTable.
A11: Power Query steps | B11: Extract the ZIP. Put source_csvs in a stable folder. In Excel: Data > Get Data > From Other Sources > Blank Query > Advanced Editor. Paste the M script and replace C:\\CHANGE_ME\\source_csvs with the full path to source_csvs. Choose Close & Load.
A12: PivotChart + slicers steps | B12: Click inside the native PivotTable > PivotTable Analyze > PivotChart. Then PivotTable Analyze > Insert Slicer; select Region, Product and Quarter if available as fields. Test each slicer.
A13: CIA / Git tasks from lesson PDF | B13: Still complete separately: ask CIA the required question, document insights in work log, use CIA Career tab, submit workbook to CIA for feedback, commit with the required message, push feature/week-3-day-3, and raise a PR.
